LICENSE.txt
MANIFEST.in
README.txt
requirements.txt
setup.py
ppm/__init__.py
ppm/config.py
ppm/dependencymanager.py
ppm/environmentmanager.py
ppm/main.py
ppm/packagehandler.py
ppm/registryclient.py
ppm/repositoryclient.py
ppm/settings.py
ppm/utility.py
ppm.egg-info/PKG-INFO
ppm.egg-info/SOURCES.txt
ppm.egg-info/dependency_links.txt
ppm.egg-info/entry_points.txt
ppm.egg-info/requires.txt
ppm.egg-info/top_level.txt